{
    "status": 0,
    "message": [{
            "add_time": "2019-11-25 09:25:02",
            "username": "不爽你咬我啊4",
            "comment": "去年去武当山玩了一趟,还不错"
        },
        {
            "add_time": "2019-11-25 09:25:02",
            "username": "毅24164",
            "comment": "武当山的雪景相当不错,站在山顶最高处向下看,相当壮观."
        },
        {
            "add_time": "2019-11-25 09:25:02",
            "username": "相生4",
            "comment": "有机会我也一定去看看"
        },
        {
            "add_time": "2019-11-25 09:25:02",
            "username": "肥仔4",
            "comment": "玄武,四大神兽之一,武当山的镇山天神,玄武大帝"
        },
        {
            "add_time": "2019-11-25 09:25:02",
            "username": "嘻嘻哈4",
            "comment": "金庸的小说让武当山出了名,武当山那边的人真的得感谢金庸"
        },
        {
            "add_time": "2019-11-25 09:25:02",
            "username": "用户59xxxx747386",
            "comment": "不错,人间仙境"
        },
        {
            "add_time": "2019-11-25 09:25:02",
            "username": "曲靖用户40xxxx244211",
            "comment": "云雾缭绕,喜欢这样氛围"
        },
        {
            "add_time": "2019-11-25 09:25:02",
            "username": "武汉用户88xxxx484831",
            "comment": "好像上去休仙,远离这喧嚣的世界"
        },
        {
            "add_time": "2019-11-25 09:25:02",
            "username": "武汉用户88xxxx448830",
            "comment": "我的家乡,我爱十堰!"
        }
    ]
}